soc.v
module cpu (
    input clk,
    input resetn,
    output reg [5:0] leds = 0
    //input RXD,
    //output TXD
);

    localparam N = 9;

    reg [5:0] mem[0:N];
    // init mem
    initial begin
        mem[0] = 6'b000001;
        mem[1] = 6'b000010;
        mem[2] = 6'b000100;
        mem[3] = 6'b001000;
        mem[4] = 6'b010000;
        mem[5] = 6'b100000;

        mem[6] = 6'b010000;
        mem[7] = 6'b001000;
        mem[8] = 6'b000100;
        mem[9] = 6'b000010;
    end

    reg [3:0] PC = 0;
    always @(posedge clk) begin
        leds <= mem[PC];
        PC   <= (!resetn || PC == N) ? 0 : (PC + 1);
    end
endmodule

module clk_div #(
    parameter N = 2
) (
    input  clk,
    output clk_out
);
    reg [N:0] counter = 0;

    always @(posedge clk) begin
        counter <= counter + 1;
    end

    assign clk_out = counter[N];

endmodule

module soc (
    input clk,
    input btn1,
    output [5:0] leds
);
    wire clk_slow;

    clk_div #(
        .N(100)
    ) i0 (
        .clk(clk),
        .clk_out(clk_slow)
    );

    cpu i1 (
        .clk(clk_slow),
        .resetn(btn1),
        .leds(leds)
    );


endmodule

soc_tb.v
module soc_tb ();
    reg clk = 0;
    reg btn1 = 1;
    wire [5:0] leds;

    soc uut (
        .clk (clk),
        .btn1(btn1),
        .leds(leds)
    );

    initial begin
        clk = 0;
    end

    always begin
        #1 clk = ~clk;
    end

    initial begin
        $dumpfile("soc_tb.vcd");
        $dumpvars(0, soc_tb);
        $monitor("%b", leds);
        #500 $finish;
    end
endmodule

soc_tb.vcd
$date
	Tue Aug  1 22:15:13 2023
$end
$version
	Icarus Verilog
$end
$timescale
	1s
$end
$scope module soc_tb $end
$var wire 6 ! leds [5:0] $end
$var reg 1 " btn1 $end
$var reg 1 # clk $end
$scope module uut $end
$var wire 1 " btn1 $end
$var wire 1 # clk $end
$var wire 6 $ leds [5:0] $end
$var wire 1 % clk_slow $end
$scope module i0 $end
$var wire 1 # clk $end
$var wire 1 % clk_out $end
$var reg 3 & counter [2:0] $end
$upscope $end
$scope module i1 $end
$var wire 1 % clk $end
$var wire 1 " resetn $end
$var reg 4 ' PC [3:0] $end
$var reg 6 ( leds [5:0] $end
$upscope $end
$upscope $end
$upscope $end
$enddefinitions $end
#0
$dumpvars
b0 (
b0 '
b0 &
0%
b0 $
0#
1"
b0 !
$end
#1
b1 &
1#
#2
0#
#3
b10 &
1#
#4
0#
#5
b11 &
1#
#6
0#
#7
b1 '
b1 !
b1 $
b1 (
1%
b100 &
1#
#8
0#
#9
b101 &
1#
#10
0#
#11
b110 &
1#
#12
0#
#13
b111 &
1#
#14
0#
#15
0%
b0 &
1#
#16
0#
#17
b1 &
1#
#18
0#
#19
b10 &
1#
#20
0#
#21
b11 &
1#
#22
0#
#23
b10 '
b10 !
b10 $
b10 (
1%
b100 &
1#
#24
0#
#25
b101 &
1#
#26
0#
#27
b110 &
1#
#28
0#
#29
b111 &
1#
#30
0#
#31
0%
b0 &
1#
#32
0#
#33
b1 &
1#
#34
0#
#35
b10 &
1#
#36
0#
#37
b11 &
1#
#38
0#
#39
b11 '
b100 !
b100 $
b100 (
1%
b100 &
1#
#40
0#
#41
b101 &
1#
#42
0#
#43
b110 &
1#
#44
0#
#45
b111 &
1#
#46
0#
#47
0%
b0 &
1#
#48
0#
#49
b1 &
1#
#50
0#
#51
b10 &
1#
#52
0#
#53
b11 &
1#
#54
0#
#55
b100 '
b1000 !
b1000 $
b1000 (
1%
b100 &
1#
#56
0#
#57
b101 &
1#
#58
0#
#59
b110 &
1#
#60
0#
#61
b111 &
1#
#62
0#
#63
0%
b0 &
1#
#64
0#
#65
b1 &
1#
#66
0#
#67
b10 &
1#
#68
0#
#69
b11 &
1#
#70
0#
#71
b101 '
b10000 !
b10000 $
b10000 (
1%
b100 &
1#
#72
0#
#73
b101 &
1#
#74
0#
#75
b110 &
1#
#76
0#
#77
b111 &
1#
#78
0#
#79
0%
b0 &
1#
#80
0#
#81
b1 &
1#
#82
0#
#83
b10 &
1#
#84
0#
#85
b11 &
1#
#86
0#
#87
b110 '
b100000 !
b100000 $
b100000 (
1%
b100 &
1#
#88
0#
#89
b101 &
1#
#90
0#
#91
b110 &
1#
#92
0#
#93
b111 &
1#
#94
0#
#95
0%
b0 &
1#
#96
0#
#97
b1 &
1#
#98
0#
#99
b10 &
1#
#100
0#
#101
b11 &
1#
#102
0#
#103
b111 '
b10000 !
b10000 $
b10000 (
1%
b100 &
1#
#104
0#
#105
b101 &
1#
#106
0#
#107
b110 &
1#
#108
0#
#109
b111 &
1#
#110
0#
#111
0%
b0 &
1#
#112
0#
#113
b1 &
1#
#114
0#
#115
b10 &
1#
#116
0#
#117
b11 &
1#
#118
0#
#119
b1000 '
b1000 !
b1000 $
b1000 (
1%
b100 &
1#
#120
0#
#121
b101 &
1#
#122
0#
#123
b110 &
1#
#124
0#
#125
b111 &
1#
#126
0#
#127
0%
b0 &
1#
#128
0#
#129
b1 &
1#
#130
0#
#131
b10 &
1#
#132
0#
#133
b11 &
1#
#134
0#
#135
b1001 '
b100 !
b100 $
b100 (
1%
b100 &
1#
#136
0#
#137
b101 &
1#
#138
0#
#139
b110 &
1#
#140
0#
#141
b111 &
1#
#142
0#
#143
0%
b0 &
1#
#144
0#
#145
b1 &
1#
#146
0#
#147
b10 &
1#
#148
0#
#149
b11 &
1#
#150
0#
#151
b0 '
b10 !
b10 $
b10 (
1%
b100 &
1#
#152
0#
#153
b101 &
1#
#154
0#
#155
b110 &
1#
#156
0#
#157
b111 &
1#
#158
0#
#159
0%
b0 &
1#
#160
0#
#161
b1 &
1#
#162
0#
#163
b10 &
1#
#164
0#
#165
b11 &
1#
#166
0#
#167
b1 '
b1 !
b1 $
b1 (
1%
b100 &
1#
#168
0#
#169
b101 &
1#
#170
0#
#171
b110 &
1#
#172
0#
#173
b111 &
1#
#174
0#
#175
0%
b0 &
1#
#176
0#
#177
b1 &
1#
#178
0#
#179
b10 &
1#
#180
0#
#181
b11 &
1#
#182
0#
#183
b10 '
b10 !
b10 $
b10 (
1%
b100 &
1#
#184
0#
#185
b101 &
1#
#186
0#
#187
b110 &
1#
#188
0#
#189
b111 &
1#
#190
0#
#191
0%
b0 &
1#
#192
0#
#193
b1 &
1#
#194
0#
#195
b10 &
1#
#196
0#
#197
b11 &
1#
#198
0#
#199
b11 '
b100 !
b100 $
b100 (
1%
b100 &
1#
#200
0#
#201
b101 &
1#
#202
0#
#203
b110 &
1#
#204
0#
#205
b111 &
1#
#206
0#
#207
0%
b0 &
1#
#208
0#
#209
b1 &
1#
#210
0#
#211
b10 &
1#
#212
0#
#213
b11 &
1#
#214
0#
#215
b100 '
b1000 !
b1000 $
b1000 (
1%
b100 &
1#
#216
0#
#217
b101 &
1#
#218
0#
#219
b110 &
1#
#220
0#
#221
b111 &
1#
#222
0#
#223
0%
b0 &
1#
#224
0#
#225
b1 &
1#
#226
0#
#227
b10 &
1#
#228
0#
#229
b11 &
1#
#230
0#
#231
b101 '
b10000 !
b10000 $
b10000 (
1%
b100 &
1#
#232
0#
#233
b101 &
1#
#234
0#
#235
b110 &
1#
#236
0#
#237
b111 &
1#
#238
0#
#239
0%
b0 &
1#
#240
0#
#241
b1 &
1#
#242
0#
#243
b10 &
1#
#244
0#
#245
b11 &
1#
#246
0#
#247
b110 '
b100000 !
b100000 $
b100000 (
1%
b100 &
1#
#248
0#
#249
b101 &
1#
#250
0#
#251
b110 &
1#
#252
0#
#253
b111 &
1#
#254
0#
#255
0%
b0 &
1#
#256
0#
#257
b1 &
1#
#258
0#
#259
b10 &
1#
#260
0#
#261
b11 &
1#
#262
0#
#263
b111 '
b10000 !
b10000 $
b10000 (
1%
b100 &
1#
#264
0#
#265
b101 &
1#
#266
0#
#267
b110 &
1#
#268
0#
#269
b111 &
1#
#270
0#
#271
0%
b0 &
1#
#272
0#
#273
b1 &
1#
#274
0#
#275
b10 &
1#
#276
0#
#277
b11 &
1#
#278
0#
#279
b1000 '
b1000 !
b1000 $
b1000 (
1%
b100 &
1#
#280
0#
#281
b101 &
1#
#282
0#
#283
b110 &
1#
#284
0#
#285
b111 &
1#
#286
0#
#287
0%
b0 &
1#
#288
0#
#289
b1 &
1#
#290
0#
#291
b10 &
1#
#292
0#
#293
b11 &
1#
#294
0#
#295
b1001 '
b100 !
b100 $
b100 (
1%
b100 &
1#
#296
0#
#297
b101 &
1#
#298
0#
#299
b110 &
1#
#300
0#
#301
b111 &
1#
#302
0#
#303
0%
b0 &
1#
#304
0#
#305
b1 &
1#
#306
0#
#307
b10 &
1#
#308
0#
#309
b11 &
1#
#310
0#
#311
b0 '
b10 !
b10 $
b10 (
1%
b100 &
1#
#312
0#
#313
b101 &
1#
#314
0#
#315
b110 &
1#
#316
0#
#317
b111 &
1#
#318
0#
#319
0%
b0 &
1#
#320
0#
#321
b1 &
1#
#322
0#
#323
b10 &
1#
#324
0#
#325
b11 &
1#
#326
0#
#327
b1 '
b1 !
b1 $
b1 (
1%
b100 &
1#
#328
0#
#329
b101 &
1#
#330
0#
#331
b110 &
1#
#332
0#
#333
b111 &
1#
#334
0#
#335
0%
b0 &
1#
#336
0#
#337
b1 &
1#
#338
0#
#339
b10 &
1#
#340
0#
#341
b11 &
1#
#342
0#
#343
b10 '
b10 !
b10 $
b10 (
1%
b100 &
1#
#344
0#
#345
b101 &
1#
#346
0#
#347
b110 &
1#
#348
0#
#349
b111 &
1#
#350
0#
#351
0%
b0 &
1#
#352
0#
#353
b1 &
1#
#354
0#
#355
b10 &
1#
#356
0#
#357
b11 &
1#
#358
0#
#359
b11 '
b100 !
b100 $
b100 (
1%
b100 &
1#
#360
0#
#361
b101 &
1#
#362
0#
#363
b110 &
1#
#364
0#
#365
b111 &
1#
#366
0#
#367
0%
b0 &
1#
#368
0#
#369
b1 &
1#
#370
0#
#371
b10 &
1#
#372
0#
#373
b11 &
1#
#374
0#
#375
b100 '
b1000 !
b1000 $
b1000 (
1%
b100 &
1#
#376
0#
#377
b101 &
1#
#378
0#
#379
b110 &
1#
#380
0#
#381
b111 &
1#
#382
0#
#383
0%
b0 &
1#
#384
0#
#385
b1 &
1#
#386
0#
#387
b10 &
1#
#388
0#
#389
b11 &
1#
#390
0#
#391
b101 '
b10000 !
b10000 $
b10000 (
1%
b100 &
1#
#392
0#
#393
b101 &
1#
#394
0#
#395
b110 &
1#
#396
0#
#397
b111 &
1#
#398
0#
#399
0%
b0 &
1#
#400
0#
#401
b1 &
1#
#402
0#
#403
b10 &
1#
#404
0#
#405
b11 &
1#
#406
0#
#407
b110 '
b100000 !
b100000 $
b100000 (
1%
b100 &
1#
#408
0#
#409
b101 &
1#
#410
0#
#411
b110 &
1#
#412
0#
#413
b111 &
1#
#414
0#
#415
0%
b0 &
1#
#416
0#
#417
b1 &
1#
#418
0#
#419
b10 &
1#
#420
0#
#421
b11 &
1#
#422
0#
#423
b111 '
b10000 !
b10000 $
b10000 (
1%
b100 &
1#
#424
0#
#425
b101 &
1#
#426
0#
#427
b110 &
1#
#428
0#
#429
b111 &
1#
#430
0#
#431
0%
b0 &
1#
#432
0#
#433
b1 &
1#
#434
0#
#435
b10 &
1#
#436
0#
#437
b11 &
1#
#438
0#
#439
b1000 '
b1000 !
b1000 $
b1000 (
1%
b100 &
1#
#440
0#
#441
b101 &
1#
#442
0#
#443
b110 &
1#
#444
0#
#445
b111 &
1#
#446
0#
#447
0%
b0 &
1#
#448
0#
#449
b1 &
1#
#450
0#
#451
b10 &
1#
#452
0#
#453
b11 &
1#
#454
0#
#455
b1001 '
b100 !
b100 $
b100 (
1%
b100 &
1#
#456
0#
#457
b101 &
1#
#458
0#
#459
b110 &
1#
#460
0#
#461
b111 &
1#
#462
0#
#463
0%
b0 &
1#
#464
0#
#465
b1 &
1#
#466
0#
#467
b10 &
1#
#468
0#
#469
b11 &
1#
#470
0#
#471
b0 '
b10 !
b10 $
b10 (
1%
b100 &
1#
#472
0#
#473
b101 &
1#
#474
0#
#475
b110 &
1#
#476
0#
#477
b111 &
1#
#478
0#
#479
0%
b0 &
1#
#480
0#
#481
b1 &
1#
#482
0#
#483
b10 &
1#
#484
0#
#485
b11 &
1#
#486
0#
#487
b1 '
b1 !
b1 $
b1 (
1%
b100 &
1#
#488
0#
#489
b101 &
1#
#490
0#
#491
b110 &
1#
#492
0#
#493
b111 &
1#
#494
0#
#495
0%
b0 &
1#
#496
0#
#497
b1 &
1#
#498
0#
#499
b10 &
1#
